coke/__init__.py
coke/version.py
coke-0.1.0.dev1.dist-info/DESCRIPTION.rst
coke-0.1.0.dev1.dist-info/LICENSE.txt
coke-0.1.0.dev1.dist-info/METADATA
coke-0.1.0.dev1.dist-info/RECORD
coke-0.1.0.dev1.dist-info/WHEEL
coke-0.1.0.dev1.dist-info/metadata.json
coke-0.1.0.dev1.dist-info/top_level.txt
