Metadata-Version: 2.0
Name: coke
Version: 0.1.0.dev1
Summary: Python GraphQL library
Home-page: UNKNOWN
Author: Mathias Fröjdman
Author-email: mwf@iki.fi
License: Apache 2.0
Download-URL: https://github.com/mwfrojdman/coke/archive/0.1.0.dev1.tar.gz
Project-URL: Source, https://github.com/mwfrojdman/coke
Project-URL: Tracker, https://github.com/mwfrojdman/coke/issues
Keywords: graphql
Platform: all
Classifier: Development Status :: 1 - Planning
Classifier: Intended Audience :: Developers
Classifier: License :: OSI Approved :: Apache Software License
Classifier: Operating System :: OS Independent
Classifier: Programming Language :: Python
Classifier: Programming Language :: Python :: 3
Classifier: Programming Language :: Python :: 3.5
Classifier: Programming Language :: Python :: 3.6
Classifier: Programming Language :: Python :: Implementation :: CPython
Requires-Python: >=3.5
Provides-Extra: test
Provides-Extra: test
Requires-Dist: pytest; extra == 'test'
